{
  "events": [
    {
      "at": 1773486463180,
      "type": "open",
      "messageId": "pv_1773486417287_f10b5c",
      "recipientId": null,
      "meta": {
        "mode": "pixel",
        "ua": "Mozilla/5.0 (Windows NT 10.0; Win64; x64) AppleWebKit/537.36 (KHTML, like Gecko) Chrome/146.0.0.0 Safari/537.36",
        "ip": "::1"
      }
    },
    {
      "at": 1773486463581,
      "type": "open",
      "messageId": "pv_1773486417287_f10b5c",
      "recipientId": null,
      "meta": {
        "mode": "pixel",
        "ua": "Mozilla/5.0 (Windows NT 10.0; Win64; x64) AppleWebKit/537.36 (KHTML, like Gecko) Chrome/146.0.0.0 Safari/537.36",
        "ip": "::1"
      }
    },
    {
      "at": 1773486463619,
      "type": "open",
      "messageId": "pv_1773486417287_f10b5c",
      "recipientId": null,
      "meta": {
        "mode": "pixel",
        "ua": "Mozilla/5.0 (Windows NT 10.0; Win64; x64) AppleWebKit/537.36 (KHTML, like Gecko) Chrome/146.0.0.0 Safari/537.36",
        "ip": "::1"
      }
    },
    {
      "at": 1773486469052,
      "type": "open",
      "messageId": "pv_1773486417287_f10b5c",
      "recipientId": null,
      "meta": {
        "mode": "pixel",
        "ua": "Mozilla/5.0 (Windows NT 10.0; Win64; x64) AppleWebKit/537.36 (KHTML, like Gecko) Chrome/146.0.0.0 Safari/537.36",
        "ip": "::1"
      }
    },
    {
      "at": 1773487915354,
      "type": "open",
      "messageId": "pv_1773487881889_ae22b1",
      "recipientId": null,
      "meta": {
        "mode": "pixel",
        "ua": "Mozilla/5.0 (Windows NT 10.0; Win64; x64) AppleWebKit/537.36 (KHTML, like Gecko) Chrome/146.0.0.0 Safari/537.36",
        "ip": "::1"
      }
    }
  ],
  "counters": {
    "pv_1773486417287_f10b5c": {
      "opens": 4,
      "clicks": 0,
      "downloads": 0,
      "lastOpenAt": 1773486469052,
      "lastClickAt": null,
      "lastDownloadAt": null
    },
    "pv_1773487881889_ae22b1": {
      "opens": 1,
      "clicks": 0,
      "downloads": 0,
      "lastOpenAt": 1773487915354,
      "lastClickAt": null,
      "lastDownloadAt": null
    }
  }
}